napalm_snr_di_di
