Metadata-Version: 2.1
Name: napalm-snr-di-di
Version: 0.17
Summary: driver napalm functionality for snr devices, via netmiko connection
Home-page: UNKNOWN
Author: Ilya Gulin
License: Apache 2.0
Platform: UNKNOWN
